ondewo/__init__.py
ondewo/logging/__init__.py
ondewo/logging/async_logger.py
ondewo/logging/constants.py
ondewo/logging/decorators.py
ondewo/logging/filters.py
ondewo/logging/logger.py
ondewo/logging/logger2.py
ondewo/logging/version.py
ondewo/logging/config/__init__.py
ondewo/logging/config/logging.yaml
ondewo_logging-3.5.0.dist-info/licenses/LICENSE
ondewo_logging-3.5.0.dist-info/METADATA
ondewo_logging-3.5.0.dist-info/WHEEL
ondewo_logging-3.5.0.dist-info/top_level.txt
ondewo_logging-3.5.0.dist-info/RECORD
