Metadata-Version: 2.4
Name: ondewo-logging
Version: 3.5.0
Summary: ONDEWO logging library provides custom logging for python including error handling and timing.
Home-page: https://github.com/ondewo/ondewo-logging-python
Author: Ondewo GmbH
Author-email: office@ondewo.com
Classifier: Development Status :: 4 - Beta
Classifier: Intended Audience :: Developers
Classifier: Topic :: Software Development :: Libraries
Classifier: License :: OSI Approved :: Apache Software License
Classifier: Programming Language :: Python :: 3.9
Classifier: Programming Language :: Python :: 3.10
Classifier: Programming Language :: Python :: 3.11
Classifier: Programming Language :: Python :: 3.12
Classifier: Programming Language :: Python :: 3.13
Classifier: Operating System :: OS Independent
Requires-Python: >=3.8
License-File: LICENSE
Requires-Dist: aiofiles
Requires-Dist: asyncio
Requires-Dist: fluent-logger>=0.11.1
Requires-Dist: msgpack
Requires-Dist: python_dotenv>=0.10.1
Requires-Dist: PyYAML>=5.3.1
Requires-Dist: setuptools>=59.5.0
Requires-Dist: wrapt
Dynamic: author
Dynamic: author-email
Dynamic: classifier
Dynamic: description
Dynamic: description-content-type
Dynamic: home-page
Dynamic: license-file
Dynamic: requires-dist
Dynamic: requires-python
Dynamic: summary
